django_bookdates/__init__.py
django_bookdates/admin.py
django_bookdates/apps.py
django_bookdates/forms.py
django_bookdates/migrations/0001_initial.py
django_bookdates/migrations/0002_alter_calendar_name_alter_timespan_title.py
django_bookdates/migrations/__init__.py
django_bookdates/models.py
django_bookdates/static/bootstrap-5.2.0-dist/css/bootstrap-grid.css
django_bookdates/static/bootstrap-5.2.0-dist/css/bootstrap-grid.css.map
django_bookdates/static/bootstrap-5.2.0-dist/css/bootstrap-grid.min.css
django_bookdates/static/bootstrap-5.2.0-dist/css/bootstrap-grid.min.css.map
django_bookdates/static/bootstrap-5.2.0-dist/css/bootstrap-grid.rtl.css
django_bookdates/static/bootstrap-5.2.0-dist/css/bootstrap-grid.rtl.css.map
django_bookdates/static/bootstrap-5.2.0-dist/css/bootstrap-grid.rtl.min.css
django_bookdates/static/bootstrap-5.2.0-dist/css/bootstrap-grid.rtl.min.css.map
django_bookdates/static/bootstrap-5.2.0-dist/css/bootstrap-reboot.css
django_bookdates/static/bootstrap-5.2.0-dist/css/bootstrap-reboot.css.map
django_bookdates/static/bootstrap-5.2.0-dist/css/bootstrap-reboot.min.css
django_bookdates/static/bootstrap-5.2.0-dist/css/bootstrap-reboot.min.css.map
django_bookdates/static/bootstrap-5.2.0-dist/css/bootstrap-reboot.rtl.css
django_bookdates/static/bootstrap-5.2.0-dist/css/bootstrap-reboot.rtl.css.map
django_bookdates/static/bootstrap-5.2.0-dist/css/bootstrap-reboot.rtl.min.css
django_bookdates/static/bootstrap-5.2.0-dist/css/bootstrap-reboot.rtl.min.css.map
django_bookdates/static/bootstrap-5.2.0-dist/css/bootstrap-utilities.css
django_bookdates/static/bootstrap-5.2.0-dist/css/bootstrap-utilities.css.map
django_bookdates/static/bootstrap-5.2.0-dist/css/bootstrap-utilities.min.css
django_bookdates/static/bootstrap-5.2.0-dist/css/bootstrap-utilities.min.css.map
django_bookdates/static/bootstrap-5.2.0-dist/css/bootstrap-utilities.rtl.css
django_bookdates/static/bootstrap-5.2.0-dist/css/bootstrap-utilities.rtl.css.map
django_bookdates-0.2.0.dist-info/METADATA
django_bookdates-0.2.0.dist-info/WHEEL
django_bookdates-0.2.0.dist-info/RECORD
